[
    {
        "id": 1,
        "name": "one"
    },
    {
        "id": 2,
        "name": "two"
    },
    {
        "id": 3,
        "name": "three"
    },
    {
        "id": 4,
        "name": "four"
    },
    {
        "id": 5,
        "name": "one"
    },
    {
        "id": 6,
        "name": "two"
    },
    {
        "id": 7,
        "name": "three"
    },
    {
        "id": 8,
        "name": "four"
    },
    {
        "id": 9,
        "name": "one"
    },
    {
        "id": 10,
        "name": "two"
    },
    {
        "id": 11,
        "name": "three"
    },
    {
        "id": 12,
        "name": "four"
    },
    {
        "id": 13,
        "name": "one"
    },
    {
        "id": 14,
        "name": "two"
    },
    {
        "id": 15,
        "name": "three"
    },
    {
        "id": 16,
        "name": "four"
    },
    {
        "id": 17,
        "name": "one"
    },
    {
        "id": 18,
        "name": "two"
    },
    {
        "id": 19,
        "name": "three"
    },
    {
        "id": 20,
        "name": "four"
    },
    {
        "id": 21,
        "name": "one"
    },
    {
        "id": 22,
        "name": "two"
    },
    {
        "id": 24,
        "name": "three"
    },
    {
        "id": 25,
        "name": "four"
    },
    {
        "id": 26,
        "name": "one"
    },
    {
        "id": 27,
        "name": "two"
    },
    {
        "id": 28,
        "name": "three"
    },
    {
        "id": 29,
        "name": "four"
    },
    {
        "id": 30,
        "name": "one"
    },
    {
        "id": 31,
        "name": "two"
    },
    {
        "id": 32,
        "name": "three"
    },
    {
        "id": 33,
        "name": "four"
    }
]